quapp_braket/__init__.py
quapp_braket/async_tasks/__init__.py
quapp_braket/async_tasks/braket_circuit_export_task.py
quapp_braket/component/__init__.py
quapp_braket/component/backend/__init__.py
quapp_braket/component/backend/braket_invocation.py
quapp_braket/component/backend/braket_job_fetching.py
quapp_braket/constant/__init__.py
quapp_braket/constant/authentication_const.py
quapp_braket/constant/job_result_const.py
quapp_braket/constant/job_status_const.py
quapp_braket/factory/__init__.py
quapp_braket/factory/braket_device_factory.py
quapp_braket/factory/braket_handler_factory.py
quapp_braket/factory/braket_provider_factory.py
quapp_braket/handler/__init__.py
quapp_braket/handler/invocation_handler.py
quapp_braket/handler/job_fetching_handler.py
quapp_braket/model/__init__.py
quapp_braket/model/device/__init__.py
quapp_braket/model/device/aws_braket_device.py
quapp_braket/model/device/oqc_cloud_device.py
quapp_braket/model/device/qapp_braket_device.py
quapp_braket/model/provider/__init__.py
quapp_braket/model/provider/aws_braket_provider.py
quapp_braket/model/provider/oqc_cloud_provider.py
quapp_braket/model/provider/qapp_braket_provider.py
quapp_braket/util/__init__.py
quapp_braket/util/braket_utils.py
quapp_braket/util/circuit_convert_utils.py
quapp_braket/util/provider_job_utils.py
quapp_braket-0.0.11.dev14.dist-info/licenses/LICENSE
quapp_braket-0.0.11.dev14.dist-info/METADATA
quapp_braket-0.0.11.dev14.dist-info/WHEEL
quapp_braket-0.0.11.dev14.dist-info/top_level.txt
quapp_braket-0.0.11.dev14.dist-info/RECORD
