Metadata-Version: 2.4
Name: quapp-braket
Version: 0.0.11.dev14
Summary: Quapp braket library supporting Quapp Platform for Quantum Computing
Author-email: "CITYNOW Co. Ltd. " <corp@citynow.vn>
License: The MIT License (MIT)
Project-URL: Homepage, https://citynow.asia/
Keywords: quapp,quapp-braket,braket,quantum
Classifier: License :: OSI Approved :: MIT License
Classifier: Programming Language :: Python
Classifier: Programming Language :: Python :: 3
Requires-Python: >=3.7
License-File: LICENSE
Requires-Dist: quapp-common==0.0.11.dev7
Requires-Dist: amazon-braket-sdk==1.83.0
Requires-Dist: oqc-qcaas-client==3.20.0
Requires-Dist: qiskit==1.4.3
Requires-Dist: pytket<3,>=2.3
Requires-Dist: pytket-braket
Requires-Dist: pymorphous
Provides-Extra: dev
Requires-Dist: black; extra == "dev"
Requires-Dist: bumpver; extra == "dev"
Requires-Dist: isort; extra == "dev"
Requires-Dist: pip-tools; extra == "dev"
Requires-Dist: pytest; extra == "dev"
Dynamic: license-file
